bgtask/__init__.py
bgtask/admin.py
bgtask/apps.py
bgtask/client.py
bgtask/core.py
bgtask/models.py
bgtask/management/__init__.py
bgtask/management/commands/__init__.py
bgtask/management/commands/bgtaskserver.py
bgtask/migrations/0001_initial.py
bgtask/migrations/__init__.py
bgtask4django-1.0.2.dist-info/LICENSE.txt
bgtask4django-1.0.2.dist-info/METADATA
bgtask4django-1.0.2.dist-info/WHEEL
bgtask4django-1.0.2.dist-info/top_level.txt
bgtask4django-1.0.2.dist-info/RECORD
