Metadata-Version: 2.1
Name: bgtask4django
Version: 1.0.2
Summary: A Django app for background task 
Home-page: https://github.com/leiyang23/django-bgtask
Author: leon_yang
Author-email: leiyang_ace@163.com
Classifier: Programming Language :: Python :: 3
Classifier: License :: OSI Approved :: MIT License
Classifier: Operating System :: OS Independent
Requires-Python: >=3.6
License-File: LICENSE.txt
